nuvu_scan/__init__.py
nuvu_scan/cli/__init__.py
nuvu_scan/cli/main.py
nuvu_scan/cli/commands/__init__.py
nuvu_scan/cli/commands/scan.py
nuvu_scan/cli/formatters/__init__.py
nuvu_scan/cli/formatters/csv.py
nuvu_scan/cli/formatters/html.py
nuvu_scan/cli/formatters/json.py
nuvu_scan/core/__init__.py
nuvu_scan/core/base.py
nuvu_scan/core/analyzers/__init__.py
nuvu_scan/core/models/__init__.py
nuvu_scan/core/providers/__init__.py
nuvu_scan/core/providers/aws/__init__.py
nuvu_scan/core/providers/aws/aws_scanner.py
nuvu_scan/core/providers/aws/collectors/__init__.py
nuvu_scan/core/providers/aws/collectors/athena.py
nuvu_scan/core/providers/aws/collectors/cost_explorer.py
nuvu_scan/core/providers/aws/collectors/glue.py
nuvu_scan/core/providers/aws/collectors/iam.py
nuvu_scan/core/providers/aws/collectors/mwaa.py
nuvu_scan/core/providers/aws/collectors/redshift.py
nuvu_scan/core/providers/aws/collectors/s3.py
nuvu_scan/core/providers/gcp/__init__.py
nuvu_scan/core/providers/gcp/gcp_scanner.py
nuvu_scan/core/providers/gcp/collectors/__init__.py
nuvu_scan/core/providers/gcp/collectors/bigquery.py
nuvu_scan/core/providers/gcp/collectors/billing.py
nuvu_scan/core/providers/gcp/collectors/dataproc.py
nuvu_scan/core/providers/gcp/collectors/gcs.py
nuvu_scan/core/providers/gcp/collectors/gemini.py
nuvu_scan/core/providers/gcp/collectors/iam.py
nuvu_scan/core/providers/gcp/collectors/pubsub.py
nuvu_scan-2.0.0.dist-info/METADATA
nuvu_scan-2.0.0.dist-info/WHEEL
nuvu_scan-2.0.0.dist-info/entry_points.txt
nuvu_scan-2.0.0.dist-info/RECORD
