Metadata-Version: 2.4
Name: nuvu-scan
Version: 2.0.0
Summary: Multi-Cloud Data Asset Control - Discover, govern, and optimize your cloud data assets across AWS and GCP
Project-URL: Homepage, https://nuvu.dev
Project-URL: Documentation, https://github.com/nuvudev/nuvu-scan#readme
Project-URL: Repository, https://github.com/nuvudev/nuvu-scan
Project-URL: Issues, https://github.com/nuvudev/nuvu-scan/issues
Project-URL: Changelog, https://github.com/nuvudev/nuvu-scan/blob/main/CHANGELOG.md
Author-email: Nuvu <info@nuvu.dev>
License: Apache-2.0
Keywords: aws,bigquery,cloud,cost-optimization,data,data-catalog,gcp,glue,governance,infrastructure,redshift,s3,scanning
Classifier: Development Status :: 4 - Beta
Classifier: Environment :: Console
Classifier: Intended Audience :: Developers
Classifier: Intended Audience :: System Administrators
Classifier: License :: OSI Approved :: Apache Software License
Classifier: Operating System :: OS Independent
Classifier: Programming Language :: Python :: 3
Classifier: Programming Language :: Python :: 3.10
Classifier: Programming Language :: Python :: 3.11
Classifier: Programming Language :: Python :: 3.12
Classifier: Programming Language :: Python :: 3.13
Classifier: Topic :: Database :: Database Engines/Servers
Classifier: Topic :: System :: Systems Administration
Requires-Python: >=3.10
Requires-Dist: boto3>=1.28.0
Requires-Dist: botocore>=1.31.0
Requires-Dist: click>=8.0.0
Requires-Dist: google-api-python-client>=2.100.0
Requires-Dist: google-auth>=2.23.0
Requires-Dist: google-cloud-bigquery>=3.11.0
Requires-Dist: google-cloud-billing>=1.11.0
Requires-Dist: google-cloud-dataproc>=5.4.0
Requires-Dist: google-cloud-monitoring>=2.16.0
Requires-Dist: google-cloud-pubsub>=2.18.0
Requires-Dist: google-cloud-storage>=2.10.0
Provides-Extra: dev
Requires-Dist: bandit>=1.7.0; extra == 'dev'
Requires-Dist: boto3-stubs[essential]>=1.28.0; extra == 'dev'
Requires-Dist: mypy>=1.0.0; extra == 'dev'
Requires-Dist: pre-commit>=3.5.0; extra == 'dev'
Requires-Dist: pytest-cov>=4.0.0; extra == 'dev'
Requires-Dist: pytest>=7.0.0; extra == 'dev'
Requires-Dist: ruff>=0.8.0; extra == 'dev'
